Metadata-Version: 2.1
Name: inStrain
Version: 1.10.0
Summary: Calculation of strain-level metrics
Home-page: https://github.com/MrOlm/inStrain
Author: Matt Olm and Alex Crits-Christoph
Author-email: mattolm@berkeley.edu
License: MIT
Requires-Python: >=3.4.0
License-File: LICENSE
Requires-Dist: numpy
Requires-Dist: pandas!=1.1.3,>=0.25
Requires-Dist: seaborn
Requires-Dist: matplotlib
Requires-Dist: biopython<=1.74
Requires-Dist: tqdm
Requires-Dist: pysam>=0.15
Requires-Dist: networkx
Requires-Dist: h5py
Requires-Dist: psutil
Requires-Dist: lmfit
Requires-Dist: pytest
